{
  "project_info": {
    "project_number": "405736329483",
    "firebase_url": "https://cardapiosapp-a67e6.firebaseio.com",
    "project_id": "cardapiosapp-a67e6",
    "storage_bucket": "cardapiosapp-a67e6.appspot.com"
  },
  "client": [
    {
      "client_info": {
        "mobilesdk_app_id": "1:405736329483:android:425a66560a40cb30",
        "android_client_info": {
          "package_name": "com.perozzo.cardapiosapp"
        }
      },
      "oauth_client": [
        {
          "client_id": "405736329483-qlbjbnap3fvr5bgdanamvqi9sfa148qt.apps.googleusercontent.com",
          "client_type": 3
        }
      ],
      "api_key": [
        {
          "current_key": "AIzaSyCNaJVV9wFC8jG9tzYYB2MZiXpuOuOxv-I"
        }
      ],
      "services": {
        "analytics_service": {
          "status": 1
        },
        "appinvite_service": {
          "status": 1,
          "other_platform_oauth_client": []
        },
        "ads_service": {
          "status": 2
        }
      }
    }
  ],
  "configuration_version": "1"
}